geofence/__init__.py
geofence/core.py
geofence-0.1.0.dist-info/METADATA
geofence-0.1.0.dist-info/WHEEL
geofence-0.1.0.dist-info/top_level.txt
geofence-0.1.0.dist-info/RECORD
